{
  "lookup": {
    "rules": {
      "[{\"prev_action\": {\"action_name\": \"action_listen\"}, \"user\": {\"intent\": \"pregunta_servicios_estudiantiles\"}}]": "utter_serviciosEstudiantiles",
      "[{\"prev_action\": {\"action_name\": \"action_listen\"}, \"user\": {\"intent\": \"pregunta_servicios_estudiantiles\"}}, {\"prev_action\": {\"action_name\": \"utter_serviciosEstudiantiles\"}, \"user\": {\"intent\": \"pregunta_servicios_estudiantiles\"}}]": "action_listen",
      "[{\"prev_action\": {\"action_name\": \"action_listen\"}, \"user\": {\"intent\": \"pregunta_que_es_cosie\"}}]": "utter_cosie",
      "[{\"prev_action\": {\"action_name\": \"action_listen\"}, \"user\": {\"intent\": \"pregunta_que_es_cosie\"}}, {\"prev_action\": {\"action_name\": \"utter_cosie\"}, \"user\": {\"intent\": \"pregunta_que_es_cosie\"}}]": "action_listen",
      "[{\"prev_action\": {\"action_name\": \"action_listen\"}, \"user\": {\"intent\": \"objetivo_cosie\"}}]": "utter_objetivo_cosie",
      "[{\"prev_action\": {\"action_name\": \"action_listen\"}, \"user\": {\"intent\": \"objetivo_cosie\"}}, {\"prev_action\": {\"action_name\": \"utter_objetivo_cosie\"}, \"user\": {\"intent\": \"objetivo_cosie\"}}]": "action_listen",
      "[{\"prev_action\": {\"action_name\": \"action_listen\"}, \"user\": {\"intent\": \"pregunta_subdirector\"}}]": "utter_quienSubdirector",
      "[{\"prev_action\": {\"action_name\": \"action_listen\"}, \"user\": {\"intent\": \"pregunta_subdirector\"}}, {\"prev_action\": {\"action_name\": \"utter_quienSubdirector\"}, \"user\": {\"intent\": \"pregunta_subdirector\"}}]": "action_listen",
      "[{\"prev_action\": {\"action_name\": \"action_listen\"}, \"user\": {\"intent\": \"saludar\"}}]": "utter_saludar",
      "[{\"prev_action\": {\"action_name\": \"action_listen\"}, \"user\": {\"intent\": \"saludar\"}}, {\"prev_action\": {\"action_name\": \"utter_saludar\"}, \"user\": {\"intent\": \"saludar\"}}]": "action_listen",
      "[{\"prev_action\": {\"action_name\": \"action_listen\"}, \"user\": {\"intent\": \"pregunta_constancia_peridodo_vacacional\"}}]": "utter_Constancias",
      "[{\"prev_action\": {\"action_name\": \"action_listen\"}, \"user\": {\"intent\": \"pregunta_constancia_peridodo_vacacional\"}}, {\"prev_action\": {\"action_name\": \"utter_Constancias\"}, \"user\": {\"intent\": \"pregunta_constancia_peridodo_vacacional\"}}]": "action_listen",
      "[{\"prev_action\": {\"action_name\": \"action_listen\"}, \"user\": {\"intent\": \"pregunta_politica_calidad\"}}]": "utter_politicaCalidad",
      "[{\"prev_action\": {\"action_name\": \"action_listen\"}, \"user\": {\"intent\": \"pregunta_politica_calidad\"}}, {\"prev_action\": {\"action_name\": \"utter_politicaCalidad\"}, \"user\": {\"intent\": \"pregunta_politica_calidad\"}}]": "action_listen",
      "[{\"prev_action\": {\"action_name\": \"action_listen\"}, \"user\": {\"intent\": \"pregunta_tramite_boletas_informativas\"}}]": "utter_Constancias",
      "[{\"prev_action\": {\"action_name\": \"action_listen\"}, \"user\": {\"intent\": \"pregunta_tramite_boletas_informativas\"}}, {\"prev_action\": {\"action_name\": \"utter_Constancias\"}, \"user\": {\"intent\": \"pregunta_tramite_boletas_informativas\"}}]": "action_listen",
      "[{\"prev_action\": {\"action_name\": \"action_listen\"}, \"user\": {\"intent\": \"pregunta_inteligencia_artificial\"}}]": "utter_inteligencia_artificial",
      "[{\"prev_action\": {\"action_name\": \"action_listen\"}, \"user\": {\"intent\": \"pregunta_inteligencia_artificial\"}}, {\"prev_action\": {\"action_name\": \"utter_inteligencia_artificial\"}, \"user\": {\"intent\": \"pregunta_inteligencia_artificial\"}}]": "action_listen",
      "[{\"prev_action\": {\"action_name\": \"action_listen\"}, \"user\": {\"intent\": \"pregunta_encargado_becas\"}}]": "utter_becas",
      "[{\"prev_action\": {\"action_name\": \"action_listen\"}, \"user\": {\"intent\": \"pregunta_encargado_becas\"}}, {\"prev_action\": {\"action_name\": \"utter_becas\"}, \"user\": {\"intent\": \"pregunta_encargado_becas\"}}]": "action_listen",
      "[{\"prev_action\": {\"action_name\": \"action_listen\"}, \"user\": {\"intent\": \"nlu_fallback\"}}]": "utter_default",
      "[{\"prev_action\": {\"action_name\": \"action_listen\"}, \"user\": {\"intent\": \"nlu_fallback\"}}, {\"prev_action\": {\"action_name\": \"utter_default\"}, \"user\": {\"intent\": \"nlu_fallback\"}}]": "action_listen",
      "[{\"prev_action\": {\"action_name\": \"action_listen\"}, \"user\": {\"intent\": \"tramites_cosie\"}}]": "utter_tramites_cosie",
      "[{\"prev_action\": {\"action_name\": \"action_listen\"}, \"user\": {\"intent\": \"tramites_cosie\"}}, {\"prev_action\": {\"action_name\": \"utter_tramites_cosie\"}, \"user\": {\"intent\": \"tramites_cosie\"}}]": "action_listen",
      "[{\"prev_action\": {\"action_name\": \"action_listen\"}, \"user\": {\"intent\": \"pregunta_reinscripciones\"}}]": "utter_reinscripciones",
      "[{\"prev_action\": {\"action_name\": \"action_listen\"}, \"user\": {\"intent\": \"pregunta_reinscripciones\"}}, {\"prev_action\": {\"action_name\": \"utter_reinscripciones\"}, \"user\": {\"intent\": \"pregunta_reinscripciones\"}}]": "action_listen",
      "[{\"prev_action\": {\"action_name\": \"action_listen\"}, \"user\": {\"intent\": \"actividades_culturales\"}}]": "utter_actividadesCulturales",
      "[{\"prev_action\": {\"action_name\": \"action_listen\"}, \"user\": {\"intent\": \"actividades_culturales\"}}, {\"prev_action\": {\"action_name\": \"utter_actividadesCulturales\"}, \"user\": {\"intent\": \"actividades_culturales\"}}]": "action_listen",
      "[{\"prev_action\": {\"action_name\": \"action_listen\"}, \"user\": {\"intent\": \"pregunta_inscripciones\"}}]": "utter_inscripciones",
      "[{\"prev_action\": {\"action_name\": \"action_listen\"}, \"user\": {\"intent\": \"pregunta_inscripciones\"}}, {\"prev_action\": {\"action_name\": \"utter_inscripciones\"}, \"user\": {\"intent\": \"pregunta_inscripciones\"}}]": "action_listen",
      "[{\"prev_action\": {\"action_name\": \"action_listen\"}, \"user\": {\"intent\": \"definicion_escom\"}}]": "utter_queEsEscom",
      "[{\"prev_action\": {\"action_name\": \"action_listen\"}, \"user\": {\"intent\": \"definicion_escom\"}}, {\"prev_action\": {\"action_name\": \"utter_queEsEscom\"}, \"user\": {\"intent\": \"definicion_escom\"}}]": "action_listen",
      "[{\"prev_action\": {\"action_name\": \"action_listen\"}, \"user\": {\"intent\": \"pregunta_departamento_formacion_basica\"}}]": "utter_dptoFormacionBasica",
      "[{\"prev_action\": {\"action_name\": \"action_listen\"}, \"user\": {\"intent\": \"pregunta_departamento_formacion_basica\"}}, {\"prev_action\": {\"action_name\": \"utter_dptoFormacionBasica\"}, \"user\": {\"intent\": \"pregunta_departamento_formacion_basica\"}}]": "action_listen",
      "[{\"prev_action\": {\"action_name\": \"action_listen\"}, \"user\": {\"intent\": \"atencion_gestion_escolar\"}}]": "utter_contactoGestionEscolar",
      "[{\"prev_action\": {\"action_name\": \"action_listen\"}, \"user\": {\"intent\": \"atencion_gestion_escolar\"}}, {\"prev_action\": {\"action_name\": \"utter_contactoGestionEscolar\"}, \"user\": {\"intent\": \"atencion_gestion_escolar\"}}]": "action_listen",
      "[{\"prev_action\": {\"action_name\": \"action_listen\"}, \"user\": {\"intent\": \"bot_challenge\"}}]": "utter_iamabot",
      "[{\"prev_action\": {\"action_name\": \"action_listen\"}, \"user\": {\"intent\": \"bot_challenge\"}}, {\"prev_action\": {\"action_name\": \"utter_iamabot\"}, \"user\": {\"intent\": \"bot_challenge\"}}]": "action_listen",
      "[{\"prev_action\": {\"action_name\": \"action_listen\"}, \"user\": {\"intent\": \"miembros_cosie\"}}]": "utter_miembros_cosie",
      "[{\"prev_action\": {\"action_name\": \"action_listen\"}, \"user\": {\"intent\": \"miembros_cosie\"}}, {\"prev_action\": {\"action_name\": \"utter_miembros_cosie\"}, \"user\": {\"intent\": \"miembros_cosie\"}}]": "action_listen",
      "[{\"prev_action\": {\"action_name\": \"action_listen\"}, \"user\": {\"intent\": \"pregunta_constancia_inscripcion\"}}]": "utter_Constancias",
      "[{\"prev_action\": {\"action_name\": \"action_listen\"}, \"user\": {\"intent\": \"pregunta_constancia_inscripcion\"}}, {\"prev_action\": {\"action_name\": \"utter_Constancias\"}, \"user\": {\"intent\": \"pregunta_constancia_inscripcion\"}}]": "action_listen",
      "[{\"prev_action\": {\"action_name\": \"action_listen\"}, \"user\": {\"intent\": \"pregunta_decanato\"}}]": "utter_quienDecanato",
      "[{\"prev_action\": {\"action_name\": \"action_listen\"}, \"user\": {\"intent\": \"pregunta_decanato\"}}, {\"prev_action\": {\"action_name\": \"utter_quienDecanato\"}, \"user\": {\"intent\": \"pregunta_decanato\"}}]": "action_listen",
      "[{\"prev_action\": {\"action_name\": \"action_listen\"}, \"user\": {\"intent\": \"pregunta_tramitar_baja_definitiva\"}}]": "utter_baja_definitiva",
      "[{\"prev_action\": {\"action_name\": \"action_listen\"}, \"user\": {\"intent\": \"pregunta_tramitar_baja_definitiva\"}}, {\"prev_action\": {\"action_name\": \"utter_baja_definitiva\"}, \"user\": {\"intent\": \"pregunta_tramitar_baja_definitiva\"}}]": "action_listen",
      "[{\"prev_action\": {\"action_name\": \"action_listen\"}, \"user\": {\"intent\": \"pregunta_medios_contacto_escom\"}}]": "utter_mediosContactoEscom",
      "[{\"prev_action\": {\"action_name\": \"action_listen\"}, \"user\": {\"intent\": \"pregunta_medios_contacto_escom\"}}, {\"prev_action\": {\"action_name\": \"utter_mediosContactoEscom\"}, \"user\": {\"intent\": \"pregunta_medios_contacto_escom\"}}]": "action_listen",
      "[{\"prev_action\": {\"action_name\": \"action_listen\"}, \"user\": {\"intent\": \"pregunta_tramitar_baja_temporal\"}}]": "utter_baja_temporal",
      "[{\"prev_action\": {\"action_name\": \"action_listen\"}, \"user\": {\"intent\": \"pregunta_tramitar_baja_temporal\"}}, {\"prev_action\": {\"action_name\": \"utter_baja_temporal\"}, \"user\": {\"intent\": \"pregunta_tramitar_baja_temporal\"}}]": "action_listen",
      "[{\"prev_action\": {\"action_name\": \"action_listen\"}, \"user\": {\"intent\": \"pregunta_escudo_escom\"}}]": "utter_escudoEscom",
      "[{\"prev_action\": {\"action_name\": \"action_listen\"}, \"user\": {\"intent\": \"pregunta_escudo_escom\"}}, {\"prev_action\": {\"action_name\": \"utter_escudoEscom\"}, \"user\": {\"intent\": \"pregunta_escudo_escom\"}}]": "action_listen",
      "[{\"prev_action\": {\"action_name\": \"action_listen\"}, \"user\": {\"intent\": \"pregunta_tramites\"}}]": "utter_tramites",
      "[{\"prev_action\": {\"action_name\": \"action_listen\"}, \"user\": {\"intent\": \"pregunta_tramites\"}}, {\"prev_action\": {\"action_name\": \"utter_tramites\"}, \"user\": {\"intent\": \"pregunta_tramites\"}}]": "action_listen",
      "[{\"prev_action\": {\"action_name\": \"action_listen\"}, \"user\": {\"intent\": \"programas_academicos_escom\"}}]": "utter_cuantasCarreras",
      "[{\"prev_action\": {\"action_name\": \"action_listen\"}, \"user\": {\"intent\": \"programas_academicos_escom\"}}, {\"prev_action\": {\"action_name\": \"utter_cuantasCarreras\"}, \"user\": {\"intent\": \"programas_academicos_escom\"}}]": "action_listen",
      "[{\"prev_action\": {\"action_name\": \"action_listen\"}, \"user\": {\"intent\": \"pregunta_tipos_de_becas\"}}]": "utter_tiposDeBecas",
      "[{\"prev_action\": {\"action_name\": \"action_listen\"}, \"user\": {\"intent\": \"pregunta_tipos_de_becas\"}}, {\"prev_action\": {\"action_name\": \"utter_tiposDeBecas\"}, \"user\": {\"intent\": \"pregunta_tipos_de_becas\"}}]": "action_listen",
      "[{\"prev_action\": {\"action_name\": \"action_listen\"}, \"user\": {\"intent\": \"pregunta_ciencias_datos\"}}]": "utter_ciencias_datos",
      "[{\"prev_action\": {\"action_name\": \"action_listen\"}, \"user\": {\"intent\": \"pregunta_ciencias_datos\"}}, {\"prev_action\": {\"action_name\": \"utter_ciencias_datos\"}, \"user\": {\"intent\": \"pregunta_ciencias_datos\"}}]": "action_listen",
      "[{\"prev_action\": {\"action_name\": \"action_listen\"}, \"user\": {\"intent\": \"pregunta_sistemas_computacionales\"}}]": "utter_sistemas_computacionales",
      "[{\"prev_action\": {\"action_name\": \"action_listen\"}, \"user\": {\"intent\": \"pregunta_sistemas_computacionales\"}}, {\"prev_action\": {\"action_name\": \"utter_sistemas_computacionales\"}, \"user\": {\"intent\": \"pregunta_sistemas_computacionales\"}}]": "action_listen",
      "[{\"prev_action\": {\"action_name\": \"action_listen\"}, \"user\": {\"intent\": \"pregunta_subdireccion_administrativa\"}}]": "utter_subdireccionAdmin",
      "[{\"prev_action\": {\"action_name\": \"action_listen\"}, \"user\": {\"intent\": \"pregunta_subdireccion_administrativa\"}}, {\"prev_action\": {\"action_name\": \"utter_subdireccionAdmin\"}, \"user\": {\"intent\": \"pregunta_subdireccion_administrativa\"}}]": "action_listen",
      "[{\"prev_action\": {\"action_name\": \"action_listen\"}, \"user\": {\"intent\": \"pregunta_director\"}}]": "utter_quienDirector",
      "[{\"prev_action\": {\"action_name\": \"action_listen\"}, \"user\": {\"intent\": \"pregunta_director\"}}, {\"prev_action\": {\"action_name\": \"utter_quienDirector\"}, \"user\": {\"intent\": \"pregunta_director\"}}]": "action_listen",
      "[{\"prev_action\": {\"action_name\": \"action_listen\"}, \"user\": {\"intent\": \"despedirse\"}}]": "utter_despedirse",
      "[{\"prev_action\": {\"action_name\": \"action_listen\"}, \"user\": {\"intent\": \"despedirse\"}}, {\"prev_action\": {\"action_name\": \"utter_despedirse\"}, \"user\": {\"intent\": \"despedirse\"}}]": "action_listen",
      "[{\"prev_action\": {\"action_name\": \"action_listen\"}, \"user\": {\"intent\": \"pregunta_tramite_credencial\"}}]": "utter_credencial",
      "[{\"prev_action\": {\"action_name\": \"action_listen\"}, \"user\": {\"intent\": \"pregunta_tramite_credencial\"}}, {\"prev_action\": {\"action_name\": \"utter_credencial\"}, \"user\": {\"intent\": \"pregunta_tramite_credencial\"}}]": "action_listen",
      "[{\"prev_action\": {\"action_name\": \"action_listen\"}, \"user\": {\"intent\": \"pregunta_composicion_organigrama\"}}]": "utter_comoCompuestoOrganigrama",
      "[{\"prev_action\": {\"action_name\": \"action_listen\"}, \"user\": {\"intent\": \"pregunta_composicion_organigrama\"}}, {\"prev_action\": {\"action_name\": \"utter_comoCompuestoOrganigrama\"}, \"user\": {\"intent\": \"pregunta_composicion_organigrama\"}}]": "action_listen",
      "[{\"prev_action\": {\"action_name\": \"action_listen\"}, \"user\": {\"intent\": \"pregunta_tramitar_baja_materias\"}}]": "utter_baja_materia",
      "[{\"prev_action\": {\"action_name\": \"action_listen\"}, \"user\": {\"intent\": \"pregunta_tramitar_baja_materias\"}}, {\"prev_action\": {\"action_name\": \"utter_baja_materia\"}, \"user\": {\"intent\": \"pregunta_tramitar_baja_materias\"}}]": "action_listen",
      "[{\"prev_action\": {\"action_name\": \"action_listen\"}, \"user\": {\"intent\": \"pregunta_historia_escom\"}}]": "utter_historiaEscom",
      "[{\"prev_action\": {\"action_name\": \"action_listen\"}, \"user\": {\"intent\": \"pregunta_historia_escom\"}}, {\"prev_action\": {\"action_name\": \"utter_historiaEscom\"}, \"user\": {\"intent\": \"pregunta_historia_escom\"}}]": "action_listen",
      "[{\"prev_action\": {\"action_name\": \"action_listen\"}, \"user\": {\"intent\": \"pregunta_unidad_informatica\"}}]": "utter_unidadInformatica",
      "[{\"prev_action\": {\"action_name\": \"action_listen\"}, \"user\": {\"intent\": \"pregunta_unidad_informatica\"}}, {\"prev_action\": {\"action_name\": \"utter_unidadInformatica\"}, \"user\": {\"intent\": \"pregunta_unidad_informatica\"}}]": "action_listen",
      "[{\"prev_action\": {\"action_name\": \"action_listen\"}, \"user\": {\"intent\": \"pregunta_que_es_sseis\"}}]": "utter_queEsSseis",
      "[{\"prev_action\": {\"action_name\": \"action_listen\"}, \"user\": {\"intent\": \"pregunta_que_es_sseis\"}}, {\"prev_action\": {\"action_name\": \"utter_queEsSseis\"}, \"user\": {\"intent\": \"pregunta_que_es_sseis\"}}]": "action_listen",
      "[{\"prev_action\": {\"action_name\": \"action_listen\"}, \"user\": {\"intent\": \"pregunta_constancia_estudios\"}}]": "utter_Constancias",
      "[{\"prev_action\": {\"action_name\": \"action_listen\"}, \"user\": {\"intent\": \"pregunta_constancia_estudios\"}}, {\"prev_action\": {\"action_name\": \"utter_Constancias\"}, \"user\": {\"intent\": \"pregunta_constancia_estudios\"}}]": "action_listen",
      "[{\"prev_action\": {\"action_name\": \"action_listen\"}, \"user\": {\"intent\": \"pregunta_ciencias_ingenieria_computo\"}}]": "utter_cienciaseIngenieriaCompu",
      "[{\"prev_action\": {\"action_name\": \"action_listen\"}, \"user\": {\"intent\": \"pregunta_ciencias_ingenieria_computo\"}}, {\"prev_action\": {\"action_name\": \"utter_cienciaseIngenieriaCompu\"}, \"user\": {\"intent\": \"pregunta_ciencias_ingenieria_computo\"}}]": "action_listen",
      "[{\"prev_action\": {\"action_name\": \"action_listen\"}, \"user\": {\"intent\": \"pregunta_ets\"}}]": "utter_ets",
      "[{\"prev_action\": {\"action_name\": \"action_listen\"}, \"user\": {\"intent\": \"pregunta_ets\"}}, {\"prev_action\": {\"action_name\": \"utter_ets\"}, \"user\": {\"intent\": \"pregunta_ets\"}}]": "action_listen",
      "[{\"prev_action\": {\"action_name\": \"action_listen\"}, \"user\": {\"intent\": \"pregunta_ingenieria_sistemas\"}}]": "utter_ingeSistemas",
      "[{\"prev_action\": {\"action_name\": \"action_listen\"}, \"user\": {\"intent\": \"pregunta_ingenieria_sistemas\"}}, {\"prev_action\": {\"action_name\": \"utter_ingeSistemas\"}, \"user\": {\"intent\": \"pregunta_ingenieria_sistemas\"}}]": "action_listen",
      "[{\"prev_action\": {\"action_name\": \"action_listen\"}, \"user\": {\"intent\": \"pregunta_departamento_gestion_escolar\"}}]": "utter_dptoGestionEscolar",
      "[{\"prev_action\": {\"action_name\": \"action_listen\"}, \"user\": {\"intent\": \"pregunta_departamento_gestion_escolar\"}}, {\"prev_action\": {\"action_name\": \"utter_dptoGestionEscolar\"}, \"user\": {\"intent\": \"pregunta_departamento_gestion_escolar\"}}]": "action_listen",
      "[{\"prev_action\": {\"action_name\": \"action_listen\"}, \"user\": {\"intent\": \"pregunta_mision_escom\"}}]": "utter_mision",
      "[{\"prev_action\": {\"action_name\": \"action_listen\"}, \"user\": {\"intent\": \"pregunta_mision_escom\"}}, {\"prev_action\": {\"action_name\": \"utter_mision\"}, \"user\": {\"intent\": \"pregunta_mision_escom\"}}]": "action_listen",
      "[{\"prev_action\": {\"action_name\": \"action_listen\"}, \"user\": {\"intent\": \"pregunta_vision_escom\"}}]": "utter_vision",
      "[{\"prev_action\": {\"action_name\": \"action_listen\"}, \"user\": {\"intent\": \"pregunta_vision_escom\"}}, {\"prev_action\": {\"action_name\": \"utter_vision\"}, \"user\": {\"intent\": \"pregunta_vision_escom\"}}]": "action_listen",
      "[{\"prev_action\": {\"action_name\": \"action_listen\"}, \"user\": {\"intent\": \"pregunta_ubicacion_escom\"}}]": "utter_ubicacion",
      "[{\"prev_action\": {\"action_name\": \"action_listen\"}, \"user\": {\"intent\": \"pregunta_ubicacion_escom\"}}, {\"prev_action\": {\"action_name\": \"utter_ubicacion\"}, \"user\": {\"intent\": \"pregunta_ubicacion_escom\"}}]": "action_listen",
      "[{\"prev_action\": {\"action_name\": \"action_listen\"}, \"user\": {\"intent\": \"acronimo_escom\"}}]": "utter_significadoESCOM",
      "[{\"prev_action\": {\"action_name\": \"action_listen\"}, \"user\": {\"intent\": \"acronimo_escom\"}}, {\"prev_action\": {\"action_name\": \"utter_significadoESCOM\"}, \"user\": {\"intent\": \"acronimo_escom\"}}]": "action_listen",
      "[{\"prev_action\": {\"action_name\": \"action_listen\"}, \"user\": {\"intent\": \"pregunta_coordinador_enlace\"}}]": "utter_quienCoordEnlace",
      "[{\"prev_action\": {\"action_name\": \"action_listen\"}, \"user\": {\"intent\": \"pregunta_coordinador_enlace\"}}, {\"prev_action\": {\"action_name\": \"utter_quienCoordEnlace\"}, \"user\": {\"intent\": \"pregunta_coordinador_enlace\"}}]": "action_listen",
      "[{\"prev_action\": {\"action_name\": \"action_listen\"}, \"user\": {\"intent\": \"pregunta_servicios_educativos\"}}]": "utter_serviciosEducativos",
      "[{\"prev_action\": {\"action_name\": \"action_listen\"}, \"user\": {\"intent\": \"pregunta_servicios_educativos\"}}, {\"prev_action\": {\"action_name\": \"utter_serviciosEducativos\"}, \"user\": {\"intent\": \"pregunta_servicios_educativos\"}}]": "action_listen",
      "[{\"prev_action\": {\"action_name\": \"action_listen\"}, \"user\": {\"intent\": \"pregunta_tramite_boletas_certificada\"}}]": "utter_Constancias",
      "[{\"prev_action\": {\"action_name\": \"action_listen\"}, \"user\": {\"intent\": \"pregunta_tramite_boletas_certificada\"}}, {\"prev_action\": {\"action_name\": \"utter_Constancias\"}, \"user\": {\"intent\": \"pregunta_tramite_boletas_certificada\"}}]": "action_listen"
    },
    "rule_only_slots": [],
    "rule_only_loops": [],
    "rules_for_loop_unhappy_path": {},
    "rules_not_in_stories": [
      "[{\"prev_action\": {\"action_name\": \"action_listen\"}, \"user\": {\"intent\": \"pregunta_departamento_gestion_escolar\"}}]",
      "[{\"prev_action\": {\"action_name\": \"action_listen\"}, \"user\": {\"intent\": \"pregunta_tramites\"}}, {\"prev_action\": {\"action_name\": \"utter_tramites\"}, \"user\": {\"intent\": \"pregunta_tramites\"}}]",
      "[{\"prev_action\": {\"action_name\": \"action_listen\"}, \"user\": {\"intent\": \"pregunta_constancia_estudios\"}}]",
      "[{\"prev_action\": {\"action_name\": \"action_listen\"}, \"user\": {\"intent\": \"nlu_fallback\"}}, {\"prev_action\": {\"action_name\": \"utter_default\"}, \"user\": {\"intent\": \"nlu_fallback\"}}]",
      "[{\"prev_action\": {\"action_name\": \"action_listen\"}, \"user\": {\"intent\": \"pregunta_tramitar_baja_temporal\"}}, {\"prev_action\": {\"action_name\": \"utter_baja_temporal\"}, \"user\": {\"intent\": \"pregunta_tramitar_baja_temporal\"}}]",
      "[{\"prev_action\": {\"action_name\": \"action_listen\"}, \"user\": {\"intent\": \"pregunta_coordinador_enlace\"}}, {\"prev_action\": {\"action_name\": \"utter_quienCoordEnlace\"}, \"user\": {\"intent\": \"pregunta_coordinador_enlace\"}}]",
      "[{\"prev_action\": {\"action_name\": \"action_listen\"}, \"user\": {\"intent\": \"pregunta_historia_escom\"}}]",
      "[{\"prev_action\": {\"action_name\": \"action_listen\"}, \"user\": {\"intent\": \"miembros_cosie\"}}]",
      "[{\"prev_action\": {\"action_name\": \"action_listen\"}, \"user\": {\"intent\": \"pregunta_subdirector\"}}, {\"prev_action\": {\"action_name\": \"utter_quienSubdirector\"}, \"user\": {\"intent\": \"pregunta_subdirector\"}}]",
      "[{\"prev_action\": {\"action_name\": \"action_listen\"}, \"user\": {\"intent\": \"pregunta_constancia_inscripcion\"}}]",
      "[{\"prev_action\": {\"action_name\": \"action_listen\"}, \"user\": {\"intent\": \"pregunta_medios_contacto_escom\"}}, {\"prev_action\": {\"action_name\": \"utter_mediosContactoEscom\"}, \"user\": {\"intent\": \"pregunta_medios_contacto_escom\"}}]",
      "[{\"prev_action\": {\"action_name\": \"action_listen\"}, \"user\": {\"intent\": \"pregunta_tramite_boletas_certificada\"}}, {\"prev_action\": {\"action_name\": \"utter_Constancias\"}, \"user\": {\"intent\": \"pregunta_tramite_boletas_certificada\"}}]",
      "[{\"prev_action\": {\"action_name\": \"action_listen\"}, \"user\": {\"intent\": \"pregunta_que_es_cosie\"}}]",
      "[{\"prev_action\": {\"action_name\": \"action_listen\"}, \"user\": {\"intent\": \"actividades_culturales\"}}]",
      "[{\"prev_action\": {\"action_name\": \"action_listen\"}, \"user\": {\"intent\": \"pregunta_escudo_escom\"}}]",
      "[{\"prev_action\": {\"action_name\": \"action_listen\"}, \"user\": {\"intent\": \"pregunta_sistemas_computacionales\"}}]",
      "[{\"prev_action\": {\"action_name\": \"action_listen\"}, \"user\": {\"intent\": \"pregunta_tramitar_baja_temporal\"}}]",
      "[{\"prev_action\": {\"action_name\": \"action_listen\"}, \"user\": {\"intent\": \"pregunta_mision_escom\"}}]",
      "[{\"prev_action\": {\"action_name\": \"action_listen\"}, \"user\": {\"intent\": \"pregunta_servicios_educativos\"}}]",
      "[{\"prev_action\": {\"action_name\": \"action_listen\"}, \"user\": {\"intent\": \"pregunta_que_es_sseis\"}}, {\"prev_action\": {\"action_name\": \"utter_queEsSseis\"}, \"user\": {\"intent\": \"pregunta_que_es_sseis\"}}]",
      "[{\"prev_action\": {\"action_name\": \"action_listen\"}, \"user\": {\"intent\": \"pregunta_tramitar_baja_materias\"}}]",
      "[{\"prev_action\": {\"action_name\": \"action_listen\"}, \"user\": {\"intent\": \"pregunta_vision_escom\"}}, {\"prev_action\": {\"action_name\": \"utter_vision\"}, \"user\": {\"intent\": \"pregunta_vision_escom\"}}]",
      "[{\"prev_action\": {\"action_name\": \"action_listen\"}, \"user\": {\"intent\": \"pregunta_decanato\"}}, {\"prev_action\": {\"action_name\": \"utter_quienDecanato\"}, \"user\": {\"intent\": \"pregunta_decanato\"}}]",
      "[{\"prev_action\": {\"action_name\": \"action_listen\"}, \"user\": {\"intent\": \"pregunta_composicion_organigrama\"}}, {\"prev_action\": {\"action_name\": \"utter_comoCompuestoOrganigrama\"}, \"user\": {\"intent\": \"pregunta_composicion_organigrama\"}}]",
      "predicting default action with intent session_start",
      "[{\"prev_action\": {\"action_name\": \"action_listen\"}, \"user\": {\"intent\": \"pregunta_ingenieria_sistemas\"}}]",
      "[{\"prev_action\": {\"action_name\": \"action_listen\"}, \"user\": {\"intent\": \"definicion_escom\"}}, {\"prev_action\": {\"action_name\": \"utter_queEsEscom\"}, \"user\": {\"intent\": \"definicion_escom\"}}]",
      "[{\"prev_action\": {\"action_name\": \"action_listen\"}, \"user\": {\"intent\": \"pregunta_ets\"}}, {\"prev_action\": {\"action_name\": \"utter_ets\"}, \"user\": {\"intent\": \"pregunta_ets\"}}]",
      "[{\"prev_action\": {\"action_name\": \"action_listen\"}, \"user\": {\"intent\": \"despedirse\"}}]",
      "[{\"prev_action\": {\"action_name\": \"action_listen\"}, \"user\": {\"intent\": \"pregunta_unidad_informatica\"}}]",
      "[{\"prev_action\": {\"action_name\": \"action_listen\"}, \"user\": {\"intent\": \"pregunta_director\"}}, {\"prev_action\": {\"action_name\": \"utter_quienDirector\"}, \"user\": {\"intent\": \"pregunta_director\"}}]",
      "[{\"prev_action\": {\"action_name\": \"action_listen\"}, \"user\": {\"intent\": \"pregunta_tramite_credencial\"}}, {\"prev_action\": {\"action_name\": \"utter_credencial\"}, \"user\": {\"intent\": \"pregunta_tramite_credencial\"}}]",
      "[{\"prev_action\": {\"action_name\": \"action_listen\"}, \"user\": {\"intent\": \"saludar\"}}, {\"prev_action\": {\"action_name\": \"utter_saludar\"}, \"user\": {\"intent\": \"saludar\"}}]",
      "[{\"prev_action\": {\"action_name\": \"action_listen\"}, \"user\": {\"intent\": \"pregunta_inscripciones\"}}, {\"prev_action\": {\"action_name\": \"utter_inscripciones\"}, \"user\": {\"intent\": \"pregunta_inscripciones\"}}]",
      "[{\"prev_action\": {\"action_name\": \"action_listen\"}, \"user\": {\"intent\": \"pregunta_ubicacion_escom\"}}, {\"prev_action\": {\"action_name\": \"utter_ubicacion\"}, \"user\": {\"intent\": \"pregunta_ubicacion_escom\"}}]",
      "[{\"prev_action\": {\"action_name\": \"action_listen\"}, \"user\": {\"intent\": \"pregunta_ciencias_ingenieria_computo\"}}]",
      "[{\"prev_action\": {\"action_name\": \"action_listen\"}, \"user\": {\"intent\": \"pregunta_unidad_informatica\"}}, {\"prev_action\": {\"action_name\": \"utter_unidadInformatica\"}, \"user\": {\"intent\": \"pregunta_unidad_informatica\"}}]",
      "[{\"prev_action\": {\"action_name\": \"action_listen\"}, \"user\": {\"intent\": \"pregunta_encargado_becas\"}}, {\"prev_action\": {\"action_name\": \"utter_becas\"}, \"user\": {\"intent\": \"pregunta_encargado_becas\"}}]",
      "[{\"prev_action\": {\"action_name\": \"action_listen\"}, \"user\": {\"intent\": \"pregunta_servicios_estudiantiles\"}}, {\"prev_action\": {\"action_name\": \"utter_serviciosEstudiantiles\"}, \"user\": {\"intent\": \"pregunta_servicios_estudiantiles\"}}]",
      "predicting default action with intent back",
      "[{\"prev_action\": {\"action_name\": \"action_listen\"}, \"user\": {\"intent\": \"pregunta_subdireccion_administrativa\"}}, {\"prev_action\": {\"action_name\": \"utter_subdireccionAdmin\"}, \"user\": {\"intent\": \"pregunta_subdireccion_administrativa\"}}]",
      "[{\"prev_action\": {\"action_name\": \"action_listen\"}, \"user\": {\"intent\": \"pregunta_inteligencia_artificial\"}}, {\"prev_action\": {\"action_name\": \"utter_inteligencia_artificial\"}, \"user\": {\"intent\": \"pregunta_inteligencia_artificial\"}}]",
      "[{\"prev_action\": {\"action_name\": \"action_listen\"}, \"user\": {\"intent\": \"pregunta_tramitar_baja_definitiva\"}}]",
      "[{\"prev_action\": {\"action_name\": \"action_listen\"}, \"user\": {\"intent\": \"pregunta_ciencias_datos\"}}]",
      "[{\"prev_action\": {\"action_name\": \"action_listen\"}, \"user\": {\"intent\": \"pregunta_inscripciones\"}}]",
      "[{\"prev_action\": {\"action_name\": \"action_listen\"}, \"user\": {\"intent\": \"programas_academicos_escom\"}}, {\"prev_action\": {\"action_name\": \"utter_cuantasCarreras\"}, \"user\": {\"intent\": \"programas_academicos_escom\"}}]",
      "[{\"prev_action\": {\"action_name\": \"action_listen\"}, \"user\": {\"intent\": \"pregunta_mision_escom\"}}, {\"prev_action\": {\"action_name\": \"utter_mision\"}, \"user\": {\"intent\": \"pregunta_mision_escom\"}}]",
      "[{\"prev_action\": {\"action_name\": \"action_listen\"}, \"user\": {\"intent\": \"pregunta_coordinador_enlace\"}}]",
      "[{\"prev_action\": {\"action_name\": \"action_listen\"}, \"user\": {\"intent\": \"objetivo_cosie\"}}, {\"prev_action\": {\"action_name\": \"utter_objetivo_cosie\"}, \"user\": {\"intent\": \"objetivo_cosie\"}}]",
      "[{\"prev_action\": {\"action_name\": \"action_listen\"}, \"user\": {\"intent\": \"acronimo_escom\"}}]",
      "[{\"prev_action\": {\"action_name\": \"action_listen\"}, \"user\": {\"intent\": \"pregunta_ingenieria_sistemas\"}}, {\"prev_action\": {\"action_name\": \"utter_ingeSistemas\"}, \"user\": {\"intent\": \"pregunta_ingenieria_sistemas\"}}]",
      "[{\"prev_action\": {\"action_name\": \"action_listen\"}, \"user\": {\"intent\": \"programas_academicos_escom\"}}]",
      "[{\"prev_action\": {\"action_name\": \"action_listen\"}, \"user\": {\"intent\": \"pregunta_tramitar_baja_definitiva\"}}, {\"prev_action\": {\"action_name\": \"utter_baja_definitiva\"}, \"user\": {\"intent\": \"pregunta_tramitar_baja_definitiva\"}}]",
      "[{\"prev_action\": {\"action_name\": \"action_listen\"}, \"user\": {\"intent\": \"pregunta_medios_contacto_escom\"}}]",
      "[{\"prev_action\": {\"action_name\": \"action_listen\"}, \"user\": {\"intent\": \"pregunta_constancia_estudios\"}}, {\"prev_action\": {\"action_name\": \"utter_Constancias\"}, \"user\": {\"intent\": \"pregunta_constancia_estudios\"}}]",
      "[{\"prev_action\": {\"action_name\": \"action_listen\"}, \"user\": {\"intent\": \"bot_challenge\"}}]",
      "[{\"prev_action\": {\"action_name\": \"action_listen\"}, \"user\": {\"intent\": \"objetivo_cosie\"}}]",
      "[{\"prev_action\": {\"action_name\": \"action_listen\"}, \"user\": {\"intent\": \"pregunta_que_es_sseis\"}}]",
      "[{\"prev_action\": {\"action_name\": \"action_listen\"}, \"user\": {\"intent\": \"pregunta_ubicacion_escom\"}}]",
      "[{\"prev_action\": {\"action_name\": \"action_listen\"}, \"user\": {\"intent\": \"tramites_cosie\"}}]",
      "[{\"prev_action\": {\"action_name\": \"action_listen\"}, \"user\": {\"intent\": \"pregunta_constancia_peridodo_vacacional\"}}, {\"prev_action\": {\"action_name\": \"utter_Constancias\"}, \"user\": {\"intent\": \"pregunta_constancia_peridodo_vacacional\"}}]",
      "[{\"prev_action\": {\"action_name\": \"action_listen\"}, \"user\": {\"intent\": \"saludar\"}}]",
      "[{\"prev_action\": {\"action_name\": \"action_listen\"}, \"user\": {\"intent\": \"pregunta_historia_escom\"}}, {\"prev_action\": {\"action_name\": \"utter_historiaEscom\"}, \"user\": {\"intent\": \"pregunta_historia_escom\"}}]",
      "[{\"prev_action\": {\"action_name\": \"action_listen\"}, \"user\": {\"intent\": \"pregunta_servicios_educativos\"}}, {\"prev_action\": {\"action_name\": \"utter_serviciosEducativos\"}, \"user\": {\"intent\": \"pregunta_servicios_educativos\"}}]",
      "[{\"prev_action\": {\"action_name\": \"action_listen\"}, \"user\": {\"intent\": \"bot_challenge\"}}, {\"prev_action\": {\"action_name\": \"utter_iamabot\"}, \"user\": {\"intent\": \"bot_challenge\"}}]",
      "[{\"prev_action\": {\"action_name\": \"action_listen\"}, \"user\": {\"intent\": \"despedirse\"}}, {\"prev_action\": {\"action_name\": \"utter_despedirse\"}, \"user\": {\"intent\": \"despedirse\"}}]",
      "[{\"prev_action\": {\"action_name\": \"action_listen\"}, \"user\": {\"intent\": \"pregunta_tipos_de_becas\"}}, {\"prev_action\": {\"action_name\": \"utter_tiposDeBecas\"}, \"user\": {\"intent\": \"pregunta_tipos_de_becas\"}}]",
      "[{\"prev_action\": {\"action_name\": \"action_listen\"}, \"user\": {\"intent\": \"pregunta_director\"}}]",
      "[{\"prev_action\": {\"action_name\": \"action_listen\"}, \"user\": {\"intent\": \"pregunta_que_es_cosie\"}}, {\"prev_action\": {\"action_name\": \"utter_cosie\"}, \"user\": {\"intent\": \"pregunta_que_es_cosie\"}}]",
      "[{\"prev_action\": {\"action_name\": \"action_listen\"}, \"user\": {\"intent\": \"pregunta_vision_escom\"}}]",
      "[{\"prev_action\": {\"action_name\": \"action_listen\"}, \"user\": {\"intent\": \"pregunta_constancia_inscripcion\"}}, {\"prev_action\": {\"action_name\": \"utter_Constancias\"}, \"user\": {\"intent\": \"pregunta_constancia_inscripcion\"}}]",
      "[{\"prev_action\": {\"action_name\": \"action_listen\"}, \"user\": {\"intent\": \"pregunta_reinscripciones\"}}]",
      "[{\"prev_action\": {\"action_name\": \"action_listen\"}, \"user\": {\"intent\": \"pregunta_subdirector\"}}]",
      "[{\"prev_action\": {\"action_name\": \"action_listen\"}, \"user\": {\"intent\": \"atencion_gestion_escolar\"}}, {\"prev_action\": {\"action_name\": \"utter_contactoGestionEscolar\"}, \"user\": {\"intent\": \"atencion_gestion_escolar\"}}]",
      "[{\"prev_action\": {\"action_name\": \"action_listen\"}, \"user\": {\"intent\": \"miembros_cosie\"}}, {\"prev_action\": {\"action_name\": \"utter_miembros_cosie\"}, \"user\": {\"intent\": \"miembros_cosie\"}}]",
      "[{\"prev_action\": {\"action_name\": \"action_listen\"}, \"user\": {\"intent\": \"pregunta_servicios_estudiantiles\"}}]",
      "[{\"prev_action\": {\"action_name\": \"action_listen\"}, \"user\": {\"intent\": \"pregunta_departamento_gestion_escolar\"}}, {\"prev_action\": {\"action_name\": \"utter_dptoGestionEscolar\"}, \"user\": {\"intent\": \"pregunta_departamento_gestion_escolar\"}}]",
      "[{\"prev_action\": {\"action_name\": \"action_listen\"}, \"user\": {\"intent\": \"pregunta_tramite_boletas_informativas\"}}, {\"prev_action\": {\"action_name\": \"utter_Constancias\"}, \"user\": {\"intent\": \"pregunta_tramite_boletas_informativas\"}}]",
      "[{\"prev_action\": {\"action_name\": \"action_listen\"}, \"user\": {\"intent\": \"pregunta_politica_calidad\"}}, {\"prev_action\": {\"action_name\": \"utter_politicaCalidad\"}, \"user\": {\"intent\": \"pregunta_politica_calidad\"}}]",
      "[{\"prev_action\": {\"action_name\": \"action_listen\"}, \"user\": {\"intent\": \"actividades_culturales\"}}, {\"prev_action\": {\"action_name\": \"utter_actividadesCulturales\"}, \"user\": {\"intent\": \"actividades_culturales\"}}]",
      "predicting default action with intent restart",
      "[{\"prev_action\": {\"action_name\": \"action_listen\"}, \"user\": {\"intent\": \"pregunta_decanato\"}}]",
      "[{\"prev_action\": {\"action_name\": \"action_listen\"}, \"user\": {\"intent\": \"pregunta_tramite_boletas_informativas\"}}]",
      "[{\"prev_action\": {\"action_name\": \"action_listen\"}, \"user\": {\"intent\": \"pregunta_ets\"}}]",
      "[{\"prev_action\": {\"action_name\": \"action_listen\"}, \"user\": {\"intent\": \"pregunta_departamento_formacion_basica\"}}]",
      "[{\"prev_action\": {\"action_name\": \"action_listen\"}, \"user\": {\"intent\": \"pregunta_reinscripciones\"}}, {\"prev_action\": {\"action_name\": \"utter_reinscripciones\"}, \"user\": {\"intent\": \"pregunta_reinscripciones\"}}]",
      "[{\"prev_action\": {\"action_name\": \"action_listen\"}, \"user\": {\"intent\": \"pregunta_encargado_becas\"}}]",
      "[{\"prev_action\": {\"action_name\": \"action_listen\"}, \"user\": {\"intent\": \"pregunta_tramites\"}}]",
      "[{\"prev_action\": {\"action_name\": \"action_listen\"}, \"user\": {\"intent\": \"pregunta_constancia_peridodo_vacacional\"}}]",
      "[{\"prev_action\": {\"action_name\": \"action_listen\"}, \"user\": {\"intent\": \"pregunta_tramite_credencial\"}}]",
      "[{\"prev_action\": {\"action_name\": \"action_listen\"}, \"user\": {\"intent\": \"pregunta_tramite_boletas_certificada\"}}]",
      "[{\"prev_action\": {\"action_name\": \"action_listen\"}, \"user\": {\"intent\": \"pregunta_ciencias_datos\"}}, {\"prev_action\": {\"action_name\": \"utter_ciencias_datos\"}, \"user\": {\"intent\": \"pregunta_ciencias_datos\"}}]",
      "[{\"prev_action\": {\"action_name\": \"action_listen\"}, \"user\": {\"intent\": \"tramites_cosie\"}}, {\"prev_action\": {\"action_name\": \"utter_tramites_cosie\"}, \"user\": {\"intent\": \"tramites_cosie\"}}]",
      "[{\"prev_action\": {\"action_name\": \"action_listen\"}, \"user\": {\"intent\": \"atencion_gestion_escolar\"}}]",
      "[{\"prev_action\": {\"action_name\": \"action_listen\"}, \"user\": {\"intent\": \"nlu_fallback\"}}]",
      "[{\"prev_action\": {\"action_name\": \"action_listen\"}, \"user\": {\"intent\": \"pregunta_tramitar_baja_materias\"}}, {\"prev_action\": {\"action_name\": \"utter_baja_materia\"}, \"user\": {\"intent\": \"pregunta_tramitar_baja_materias\"}}]",
      "[{\"prev_action\": {\"action_name\": \"action_listen\"}, \"user\": {\"intent\": \"pregunta_escudo_escom\"}}, {\"prev_action\": {\"action_name\": \"utter_escudoEscom\"}, \"user\": {\"intent\": \"pregunta_escudo_escom\"}}]",
      "[{\"prev_action\": {\"action_name\": \"action_listen\"}, \"user\": {\"intent\": \"pregunta_sistemas_computacionales\"}}, {\"prev_action\": {\"action_name\": \"utter_sistemas_computacionales\"}, \"user\": {\"intent\": \"pregunta_sistemas_computacionales\"}}]",
      "[{\"prev_action\": {\"action_name\": \"action_listen\"}, \"user\": {\"intent\": \"pregunta_inteligencia_artificial\"}}]",
      "[{\"prev_action\": {\"action_name\": \"action_listen\"}, \"user\": {\"intent\": \"definicion_escom\"}}]",
      "[{\"prev_action\": {\"action_name\": \"action_listen\"}, \"user\": {\"intent\": \"acronimo_escom\"}}, {\"prev_action\": {\"action_name\": \"utter_significadoESCOM\"}, \"user\": {\"intent\": \"acronimo_escom\"}}]",
      "[{\"prev_action\": {\"action_name\": \"action_listen\"}, \"user\": {\"intent\": \"pregunta_politica_calidad\"}}]",
      "[{\"prev_action\": {\"action_name\": \"action_listen\"}, \"user\": {\"intent\": \"pregunta_ciencias_ingenieria_computo\"}}, {\"prev_action\": {\"action_name\": \"utter_cienciaseIngenieriaCompu\"}, \"user\": {\"intent\": \"pregunta_ciencias_ingenieria_computo\"}}]",
      "[{\"prev_action\": {\"action_name\": \"action_listen\"}, \"user\": {\"intent\": \"pregunta_tipos_de_becas\"}}]",
      "[{\"prev_action\": {\"action_name\": \"action_listen\"}, \"user\": {\"intent\": \"pregunta_composicion_organigrama\"}}]",
      "[{\"prev_action\": {\"action_name\": \"action_listen\"}, \"user\": {\"intent\": \"pregunta_subdireccion_administrativa\"}}]",
      "[{\"prev_action\": {\"action_name\": \"action_listen\"}, \"user\": {\"intent\": \"pregunta_departamento_formacion_basica\"}}, {\"prev_action\": {\"action_name\": \"utter_dptoFormacionBasica\"}, \"user\": {\"intent\": \"pregunta_departamento_formacion_basica\"}}]"
    ]
  }
}